fsga.py
FeatureSelectionUsingGA-1.0.0.dist-info/LICENSE.txt
FeatureSelectionUsingGA-1.0.0.dist-info/METADATA
FeatureSelectionUsingGA-1.0.0.dist-info/WHEEL
FeatureSelectionUsingGA-1.0.0.dist-info/top_level.txt
FeatureSelectionUsingGA-1.0.0.dist-info/RECORD
