Metadata-Version: 2.1
Name: FeatureSelectionUsingGA
Version: 1.0.0
Summary: Feature selection using genetic algorithms
Home-page: UNKNOWN
Author: UNKNOWN
Author-email: UNKNOWN
License: UNKNOWN
Platform: UNKNOWN
Requires-Dist: numpy (==1.22.4)
Requires-Dist: matplotlib (==3.7.1)
